django_ttag-3.0.dist-info/DESCRIPTION.rst
django_ttag-3.0.dist-info/METADATA
django_ttag-3.0.dist-info/RECORD
django_ttag-3.0.dist-info/WHEEL
django_ttag-3.0.dist-info/metadata.json
django_ttag-3.0.dist-info/top_level.txt
ttag/__init__.py
ttag/args.py
ttag/core.py
ttag/exceptions.py
ttag/models.py
ttag/utils.py
ttag/helpers/__init__.py
ttag/helpers/as_tag.py
ttag/helpers/template_tag.py
ttag/tests/__init__.py
ttag/tests/test_helpers.py
ttag/tests/test_main.py
ttag/tests/test_registration.py
ttag/tests/ttag_test_app/__init__.py
ttag/tests/ttag_test_app/models.py
ttag/tests/ttag_test_app/tags.py
ttag/tests/ttag_test_app/templatetags/__init__.py
ttag/tests/ttag_test_app/templatetags/ttag_test/__init__.py
ttag/tests/ttag_test_app/templatetags/ttag_test/as_tags.py
ttag/tests/ttag_test_app/templatetags/ttag_test/template_tags.py
