Metadata-Version: 2.0
Name: django-ttag
Version: 3.0
Summary: A template tag constructor library for Django.
Home-page: http://github.com/lincolnloop/django-ttag
Author: Chris Beaven
Author-email: chris@lincolnloop.com
License: MIT
Platform: UNKNOWN
Classifier: Development Status :: 4 - Beta
Classifier: Environment :: Web Environment
Classifier: Intended Audience :: Developers
Classifier: License :: OSI Approved :: BSD License
Classifier: Operating System :: OS Independent
Classifier: Programming Language :: Python
Classifier: Programming Language :: Python :: 2
Classifier: Programming Language :: Python :: 3
Classifier: Framework :: Django
Requires-Dist: six
